databasebaseclass/__init__.py
databasebaseclass/base.py
databasebaseclass/py.typed
databasebaseclass-0.1.1.dist-info/AUTHORS.rst
databasebaseclass-0.1.1.dist-info/METADATA
databasebaseclass-0.1.1.dist-info/WHEEL
databasebaseclass-0.1.1.dist-info/top_level.txt
databasebaseclass-0.1.1.dist-info/RECORD
