Metadata-Version: 2.1
Name: databasebaseclass
Version: 0.1.1
Summary: This is some boilerplate code that I commonly use in my database classes.
Home-page: https://github.com/city-of-baltimore/databasebaseclass
Author: Brian Seel
Author-email: Brian.Seel@baltimorecity.gov
License: MIT
Project-URL: Documentation, https://github.com/city-of-baltimore/databasebaseclass
Project-URL: Source, https://github.com/city-of-baltimore/databasebaseclass
Project-URL: Changelog, https://github.com/city-of-baltimore/databasebaseclass/commits/main
Project-URL: Tracker, https://github.com/city-of-baltimore/databasebaseclass/issues
Project-URL: Download, http://pypi.org/project/databasebaseclass/
Project-URL: Twitter, https://twitter.com/cylussec
Platform: any
Classifier: Development Status :: 4 - Beta
Classifier: Programming Language :: Python
License-File: AUTHORS.rst
Requires-Dist: loguru
Requires-Dist: sqlalchemy
Requires-Dist: importlib-metadata ; python_version < "3.8"
Provides-Extra: testing
Requires-Dist: setuptools ; extra == 'testing'
Requires-Dist: pytest ; extra == 'testing'
Requires-Dist: pytest-cov ; extra == 'testing'
